udf_tools/__init__.py
udf_tools/cli.py
udf_tools/editor.py
udf_tools/converters/__init__.py
udf_tools/converters/docx.py
udf_tools/converters/pdf.py
udf_tools/core/__init__.py
udf_tools/core/io.py
udf_tools/core/manager.py
udf_tools/models/__init__.py
udf_tools/models/document.py
udf_tools/models/elements.py
udf_tools/models/styles.py
udf_tools-0.1.0.dist-info/METADATA
udf_tools-0.1.0.dist-info/WHEEL
udf_tools-0.1.0.dist-info/entry_points.txt
udf_tools-0.1.0.dist-info/top_level.txt
udf_tools-0.1.0.dist-info/RECORD
