Metadata-Version: 2.4
Name: udf-tools
Version: 0.1.0
Summary: A comprehensive Python library for handling UYAP UDF files.
Author-email: Developer <developer@example.com>
Requires-Python: >=3.9
Requires-Dist: lxml
Requires-Dist: python-docx
Requires-Dist: reportlab
Requires-Dist: pydantic
Requires-Dist: rich
Requires-Dist: click
Requires-Dist: pillow
